dlkinematics/__init__.py
dlkinematics/dlkinematics.py
dlkinematics/solver.py
dlkinematics/tf_transformations.py
dlkinematics/training_utils.py
dlkinematics/urdf.py
dlkinematics/urdf_parser/__init__.py
dlkinematics/urdf_parser/sdf.py
dlkinematics/urdf_parser/urdf.py
dlkinematics/urdf_parser/xml_reflection/__init__.py
dlkinematics/urdf_parser/xml_reflection/basics.py
dlkinematics/urdf_parser/xml_reflection/core.py
dlkinematics-0.1.0rc4.dist-info/LICENSE
dlkinematics-0.1.0rc4.dist-info/WHEEL
dlkinematics-0.1.0rc4.dist-info/METADATA
dlkinematics-0.1.0rc4.dist-info/RECORD
