Metadata-Version: 2.1
Name: dlkinematics
Version: 0.1.0rc4
Summary: Differentiable Forward Kinematics for TensorFlow and Keras based on URDF files
Home-page: https://github.com/lumoe/dlkinematics
License: BSD 3-Clause License
Keywords: tensorflow,kinematics,forward-kinematics,urdf,robotics
Author: Lukas Mölschl
Author-email: lukas+pypi@moelschl.com
Requires-Python: >=3.8,<3.11
Classifier: License :: Other/Proprietary License
Classifier: Programming Language :: Python :: 3
Classifier: Programming Language :: Python :: 3.8
Classifier: Programming Language :: Python :: 3.9
Classifier: Programming Language :: Python :: 3.10
Requires-Dist: lxml (>=4.9.1,<5.0.0)
Requires-Dist: numpy (>=1.23.5,<2.0.0)
Requires-Dist: pyaml (>=21.10.1,<22.0.0)
Requires-Dist: pyyaml (>=6.0,<7.0)
Requires-Dist: tensorflow (>=2.2.0,<3.0.0)
Requires-Dist: tensorflow-graphics (>=2021.12.3,<2022.0.0)
Requires-Dist: transformations (>=2022.9.26,<2023.0.0)
Project-URL: Repository, https://github.com/lumoe/dlkinematics
